LICENSE.md
MANIFEST.in
README.md
rdfdict.py
setup.py
RDFdict.egg-info/PKG-INFO
RDFdict.egg-info/SOURCES.txt
RDFdict.egg-info/dependency_links.txt
RDFdict.egg-info/top_level.txt
test/test_rdfdict.py
test/test_withrdflib.py