Metadata-Version: 1.1
Name: RDFdict
Version: 0.1.6
Summary: A class for creating a nested dictionaries representation of RDF quads or triples
Home-page: http://github.com/mattclarkdotnet/rdfdict
Author: Matt Clark
Author-email: matt@mattclark.net
License: MIT
Keywords: rdf,json,dict
Platform: UNKNOWN
Classifier: Programming Language :: Python
Classifier: Programming Language :: Python :: 3
Classifier: Topic :: Software Development :: Libraries :: Python Modules
Classifier: Topic :: Text Processing
Classifier: License :: OSI Approved :: MIT License
Classifier: Intended Audience :: Developers
Classifier: Development Status :: 5 - Production/Stable
Classifier: Operating System :: OS Independent
